pytex_lib/__init__.py
pytex_lib/core.py
pytex_lib-0.1.13.dist-info/METADATA
pytex_lib-0.1.13.dist-info/WHEEL
pytex_lib-0.1.13.dist-info/top_level.txt
pytex_lib-0.1.13.dist-info/RECORD
