Metadata-Version: 2.4
Name: pytex-lib
Version: 0.1.13
Summary: Decorate your functions to direct the output to a LaTeX file.
Requires-Python: >=3.12
Requires-Dist: pathlib>=1.0.1
